eagleRpaUtility/CentralizedLogger.py
eagleRpaUtility/CustomLogger.py
eagleRpaUtility/ImageManager.py
eagleRpaUtility/Logger.py
eagleRpaUtility/RequestMaker.py
eagleRpaUtility/__init__.py
eagleRpaUtility-0.2.0.dist-info/METADATA
eagleRpaUtility-0.2.0.dist-info/WHEEL
eagleRpaUtility-0.2.0.dist-info/top_level.txt
eagleRpaUtility-0.2.0.dist-info/RECORD
