Metadata-Version: 2.1
Name: eagleRpaUtility
Version: 0.2.0
Summary: EagleProjects RPA utility function pakcage
Author: cpicciafuoco@eagleprojects.it
License: MIT
